{
    "GaussianSymmFunc_std_dev_G2_20_0": 0.021176705638680748,
    "AGNIFingerPrint_std_dev_AGNI_eta=1_23e+00": 0.01842677322043398,
    "AtomicPackingEfficiency_mean_simul__packing_efficiency": 0.009443943778230582,
    "BondFractions_O_-_P_bond_frac_": 0.008479974159789017,
    "AtomicPackingEfficiency_mean_abs_simul__packing_efficiency": 0.008305945640834256,
    "ElectronegativityDiff_minimum_EN_difference": 0.005811407814281943,
    "MEGNet_OFMEncoded_v1_11": 0.0049060812968652655,
    "ElementProperty_MagpieData_mean_CovalentRadius": 0.004768706685783743,
    "MEGNet_OFMEncoded_v1_47": 0.004506004132510975,
    "BondFractions_O_-_Si_bond_frac_": 0.003835424743805278,
    "BondFractions_Mn_-_O_bond_frac_": 0.0038018633487208334,
    "AtomicPackingEfficiency_dist_from_5_clusters__APE____0_010": 0.0037053451747645076,
    "ElementProperty_MagpieData_mean_NpValence": 0.003681092456905817,
    "GaussianSymmFunc_mean_G2_80_0": 0.0035704312974950926,
    "MEGNet_OFMEncoded_v1_27": 0.003538431864037653,
    "BondFractions_Fe_-_O_bond_frac_": 0.0033238340513849518,
    "ElementProperty_MagpieData_avg_dev_Number": 0.0031425118504305577,
    "ElementFraction_O": 0.0031241210315545295,
    "ElementFraction_Li": 0.003039663682192811,
    "MaximumPackingEfficiency_max_packing_efficiency": 0.002998903552407919,
    "Stoichiometry_0-norm": 0.0029318268362803082,
    "MEGNet_OFMEncoded_v1_180": 0.0029059830593463876,
    "MEGNet_OFMEncoded_v1_20": 0.002813750337179003,
    "IonProperty_avg_ionic_char": 0.002784473370604585,
    "BondFractions_O_-_W_bond_frac_": 0.0027247075247075537,
    "MEGNet_OFMEncoded_v1_29": 0.0026898249224443695,
    "MEGNet_OFMEncoded_v1_182": 0.0026733175467508544,
    "ElementProperty_MagpieData_maximum_GSvolume_pa": 0.0026524181433379857,
    "AtomicOrbitals_gap_AO": 0.0025988678274657044,
    "ElementProperty_MagpieData_maximum_Number": 0.0025529730338304294
}