{
    "OPSiteFingerprint_mean_bent_150_degrees_CN_2": 0.02584474760443977,
    "OPSiteFingerprint_mean_bent_120_degrees_CN_2": 0.0213757938688019,
    "XRDPowderPattern_xrd_16": 0.02054748380676425,
    "XRDPowderPattern_xrd_17": 0.019642148329003427,
    "ElementProperty_MagpieData_minimum_Number": 0.016139433285977826,
    "AGNIFingerPrint_std_dev_AGNI_dir=x_eta=1_88e+00": 0.012608777953320351,
    "CrystalNNFingerprint_mean_octahedral_CN_6": 0.011916153640755307,
    "AtomicOrbitals_HOMO_element": 0.011903457066265315,
    "BondFractions_O_-_V_bond_frac_": 0.011365228885356085,
    "MEGNet_OFMEncoded_v1_28": 0.010712347801587408,
    "VoronoiFingerprint_std_dev_Voro_dist_minimum": 0.008991903748720331,
    "ElementFraction_Pb": 0.007932912912702983,
    "DensityFeatures_packing_fraction": 0.007902549193611759,
    "ElementFraction_S": 0.007657469178837406,
    "RadialDistributionFunction_radial_distribution_function_d_1_50": 0.007509830220239041,
    "BondFractions_Ni_-_O_bond_frac_": 0.007239809815479851,
    "BondFractions_Mn_-_O_bond_frac_": 0.007068399748129658,
    "MEGNet_OFMEncoded_v1_180": 0.006273826848770052,
    "GeneralizedRDF_std_dev_Gaussian_center=7_0_width=1_0": 0.005842886965771863,
    "XRDPowderPattern_xrd_12": 0.005745957817443322,
    "CrystalNNFingerprint_std_dev_see-saw-like_CN_4": 0.0056751371714645615,
    "XRDPowderPattern_xrd_27": 0.004736447047334653,
    "OPSiteFingerprint_std_dev_q2_CN_12": 0.004698367661056879,
    "MEGNet_OFMEncoded_v1_22": 0.004615361615200078,
    "MEGNet_OFMEncoded_v1_93": 0.004426189032872074,
    "ElementFraction_V": 0.004286151321625013,
    "BondFractions_O_-_W_bond_frac_": 0.004066887340300675,
    "XRDPowderPattern_xrd_30": 0.004026925500620237,
    "ElementFraction_Br": 0.0038788320183962494,
    "ElementProperty_MagpieData_avg_dev_MeltingT": 0.003852881772741567
}